[
  {
    "id": 1,
    "title": "Compose article",
    "subtitle": "This page represents a compose article and you will learn how to make such screen using Jetpack compose.",
    "imageUrl": ""
  },
  {
    "id": 2,
    "title": "Quadrant",
    "subtitle": "In this section you will learn how to use compose wisely.",
    "imageUrl": ""
  },
  {
    "id": 3,
    "title": "Tip Calculator",
    "subtitle": "In this code lab you will learn how to build a tip calculator app.",
    "imageUrl": ""
  },
  {
    "id": 4,
    "title": "Art Space App",
    "subtitle": "In this section you will learn how to build an art space app.",
    "imageUrl": ""
  },
  {
    "id": 5,
    "title": "Lemonade",
    "subtitle": "In this section you will learn how to build an art space app.",
    "imageUrl": ""
  },
  {
    "id": 6,
    "title": "",
    "subtitle": "",
    "imageUrl": ""
  },
  {
    "id": 7,
    "title": "",
    "subtitle": "",
    "imageUrl": ""
  },
  {
    "id": 8,
    "title": "",
    "subtitle": "",
    "imageUrl": ""
  },
  {
    "id": 9,
    "title": "",
    "subtitle": "",
    "imageUrl": ""
  },
  {
    "id": 10,
    "title": "",
    "subtitle": "",
    "imageUrl": ""
  }
]